<?xml version="1.0" encoding="UTF-8"?>
<beans xmlns="http://www.springframework.org/schema/beans"
       xmlns:xsi="http://www.w3.org/2001/XMLSchema-instance"
       xmlns:security="http://www.springframework.org/schema/security"
       xsi:schemaLocation="http://www.springframework.org/schema/beans
                           http://www.springframework.org/schema/beans/spring-beans-2.5.xsd
                           http://www.springframework.org/schema/security
                           http://www.springframework.org/schema/security/spring-security-2.0.xsd">

    <security:http auto-config="true">
        <security:intercept-url pattern="/login" access="IS_AUTHENTICATED_ANONYMOUSLY" />
        <security:intercept-url pattern="/hello" access="IS_AUTHENTICATED_ANONYMOUSLY" />
        <security:intercept-url pattern="/index.html" access="IS_AUTHENTICATED_ANONYMOUSLY" />
        <security:intercept-url pattern="/app" access="IS_AUTHENTICATED_ANONYMOUSLY" />
        <security:intercept-url pattern="/static/**" access="IS_AUTHENTICATED_ANONYMOUSLY" />
        <security:intercept-url pattern="/**" access="ROLE_USER" />

        <security:form-login login-page="/login"
                             login-processing-url="/loginsubmit"
                             default-target-url="/app"
                             authentication-failure-url="/login?error=1" />

        <security:remember-me
                key="5135e99886bd5eca8c02fd6ea0980389d1f83f2d589335a5dd30573b389a88f8"/>

        <security:logout invalidate-session="true"
                         logout-url="/logout"
                         logout-success-url="/login"/>
    </security:http>

    <bean name="userDetailsService" class="com.mysite.webjdo.service.UserDetailsServiceImpl"/>

    <security:authentication-provider user-service-ref="userDetailsService"/>
</beans>